yamlio/__init__.py
yamlio/main.py
yamlio-0.1.4.dist-info/METADATA
yamlio-0.1.4.dist-info/WHEEL
yamlio-0.1.4.dist-info/entry_points.txt
yamlio-0.1.4.dist-info/licenses/LICENSE
yamlio-0.1.4.dist-info/RECORD
