Metadata-Version: 2.4
Name: yamlio
Version: 0.1.4
Summary: Library for interacting with YAML files.
Project-URL: repository, https://codeberg.org/melvinquick/yamlio
Project-URL: issues, https://codeberg.org/melvinquick/yamlio/issues
Author-email: Melvin Quick <melvinquick@proton.me>
License-Expression: MIT
License-File: LICENSE
Requires-Python: >=3.12
Requires-Dist: pyyaml>=6.0.2
